pyzx/__init__.py
pyzx/__main__.py
pyzx/altextract.py
pyzx/basicrules.py
pyzx/d3.py
pyzx/drawing.py
pyzx/editor.py
pyzx/editor_actions.py
pyzx/extract.py
pyzx/gadget_extract.py
pyzx/generate.py
pyzx/gflow.py
pyzx/hrules.py
pyzx/hsimplify.py
pyzx/io.py
pyzx/linalg.py
pyzx/mbqc.py
pyzx/optimize.py
pyzx/parity_network.py
pyzx/py.typed
pyzx/pyquil_circuit.py
pyzx/quantomatic.py
pyzx/quimb.py
pyzx/rules.py
pyzx/simplify.py
pyzx/simulate.py
pyzx/symbolic.py
pyzx/tensor.py
pyzx/tikz.py
pyzx/todd.py
pyzx/utils.py
pyzx/circuit/__init__.py
pyzx/circuit/emojiparser.py
pyzx/circuit/gates.py
pyzx/circuit/graphparser.py
pyzx/circuit/qasmparser.py
pyzx/circuit/qcparser.py
pyzx/circuit/qsimparser.py
pyzx/circuit/quipperparser.py
pyzx/circuit/sqasm.py
pyzx/graph/__init__.py
pyzx/graph/base.py
pyzx/graph/diff.py
pyzx/graph/graph.py
pyzx/graph/graph_gt.py
pyzx/graph/graph_ig.py
pyzx/graph/graph_s.py
pyzx/graph/jsonparser.py
pyzx/graph/scalar.py
pyzx/js/d3.v5.min.js
pyzx/js/zx_editor_model.js
pyzx/js/zx_editor_widget.js
pyzx/js/zx_viewer.inline.js
pyzx/js/zx_viewer.js
pyzx/local_search/__init__.py
pyzx/local_search/congruences.py
pyzx/local_search/genetic.py
pyzx/local_search/scores.py
pyzx/local_search/simulated_annealing.py
pyzx/routing/__init__.py
pyzx/routing/architecture.py
pyzx/routing/cnot_mapper.py
pyzx/routing/machine_learning.py
pyzx/routing/parity_maps.py
pyzx/routing/phase_poly.py
pyzx/routing/steiner.py
pyzx/scripts/__init__.py
pyzx/scripts/circ2circ.py
pyzx/scripts/circ2tikz.py
pyzx/scripts/circuit_router.py
pyzx/scripts/cnot_generator.py
pyzx/scripts/phase_poly_generator.py
pyzx-0.8.0.dist-info/LICENSE
pyzx-0.8.0.dist-info/METADATA
pyzx-0.8.0.dist-info/WHEEL
pyzx-0.8.0.dist-info/top_level.txt
pyzx-0.8.0.dist-info/RECORD
