Metadata-Version: 2.1
Name: pyzx
Version: 0.8.0
Summary: Library for quantum circuit rewriting and optimisation using the ZX-calculus
Home-page: https://github.com/Quantomatic/pyzx.git
Author: Quantomatic
Author-email: john@vdwetering.name
License: Apache2
Classifier: License :: OSI Approved :: Apache Software License
Classifier: Programming Language :: Python :: 3
Classifier: Programming Language :: Python :: 3.8
Classifier: Programming Language :: Python :: 3.9
Classifier: Programming Language :: Python :: 3.10
Classifier: Topic :: Software Development :: Libraries :: Python Modules
Classifier: Development Status :: 4 - Beta
Requires-Python: >=3.7
License-File: LICENSE
Requires-Dist: typing-extensions >=3.7.4
Requires-Dist: numpy >=1.14
Requires-Dist: pyperclip >=1.8.1
Requires-Dist: tqdm >=4.56.0
Requires-Dist: ipywidgets <8,>=7.5
Requires-Dist: lark ~=1.1.7
